git_recap/__init__.py
git_recap/fetcher.py
git_recap/utils.py
git_recap/providers/__init__.py
git_recap/providers/azure_fetcher.py
git_recap/providers/base_fetcher.py
git_recap/providers/github_fetcher.py
git_recap/providers/gitlab_fetcher.py
git_recap/providers/url_fetcher.py
git_recap-0.1.5.dist-info/licenses/LICENSE
git_recap-0.1.5.dist-info/METADATA
git_recap-0.1.5.dist-info/WHEEL
git_recap-0.1.5.dist-info/top_level.txt
git_recap-0.1.5.dist-info/RECORD
