Metadata-Version: 2.4
Name: git-recap
Version: 0.1.5
Summary: A modular Python tool that aggregates and formats user-authored messages from repositories.
Author: Bruno V.
Author-email: bruno.vitorino@tecnico.ulisboa.pt
Classifier: Programming Language :: Python :: 3
Classifier: License :: OSI Approved :: MIT License
Classifier: Operating System :: OS Independent
License-File: LICENSE
Requires-Dist: PyGithub==2.6.1
Requires-Dist: azure-devops==7.1.0b4
Requires-Dist: python-gitlab==5.6.0
Dynamic: author
Dynamic: author-email
Dynamic: classifier
Dynamic: description
Dynamic: description-content-type
Dynamic: license-file
Dynamic: requires-dist
Dynamic: summary
